pyonlinesim/__init__.py
pyonlinesim/clients/__init__.py
pyonlinesim/clients/rent.py
pyonlinesim/clients/sms.py
pyonlinesim/core/__init__.py
pyonlinesim/core/abc/__init__.py
pyonlinesim/core/abc/client.py
pyonlinesim/core/methods/__init__.py
pyonlinesim/exceptions/__init__.py
pyonlinesim/exceptions/authentication.py
pyonlinesim/exceptions/base.py
pyonlinesim/exceptions/rent/order.py
pyonlinesim/exceptions/sms/__init__.py
pyonlinesim/exceptions/sms/order.py
pyonlinesim/exceptions/sms/state.py
pyonlinesim/types/__init__.py
pyonlinesim/types/rent/__init__.py
pyonlinesim/types/rent/order.py
pyonlinesim/types/rent/tarrifs.py
pyonlinesim/types/sms/__init__.py
pyonlinesim/types/sms/balance.py
pyonlinesim/types/sms/manage_order.py
pyonlinesim/types/sms/number_stats.py
pyonlinesim/types/sms/order_number.py
pyonlinesim/types/sms/state.py
pyonlinesim-1.1.3.dist-info/LICENSE
pyonlinesim-1.1.3.dist-info/WHEEL
pyonlinesim-1.1.3.dist-info/METADATA
pyonlinesim-1.1.3.dist-info/RECORD
